[{"data":{"id":"Install-ReportUnit","source":null,"target":null}},{"data":{"id":"c96a6c3f-2668-4839-8d09-acaa6c0a62a6","source":"Install-ReportUnit","target":"Install-ReportGenerator"}},{"data":{"id":"Install-ReportGenerator","source":null,"target":null}},{"data":{"id":"0c2c7ee5-fe28-45d8-a3be-d5a2e275046e","source":"Install-ReportGenerator","target":"Build"}},{"data":{"id":"Build","source":null,"target":null}},{"data":{"id":"efea743f-fe68-4130-8b98-046199c25766","source":"Build","target":"Clean"}},{"data":{"id":"b135752d-abca-472d-ba4e-c0b6f1444675","source":"Build","target":"Restore"}},{"data":{"id":"Restore","source":null,"target":null}},{"data":{"id":"Clean","source":null,"target":null}},{"data":{"id":"36eb7764-e932-4a61-bd22-42af6200ce4e","source":"Clean","target":"Show-Info"}},{"data":{"id":"f6152603-ff2c-43db-b339-310f0b507238","source":"Clean","target":"Print-AppVeyor-Environment-Variables"}},{"data":{"id":"Print-AppVeyor-Environment-Variables","source":null,"target":null}},{"data":{"id":"Show-Info","source":null,"target":null}}]